examples/__init__.py
examples/common.py
examples/config.py
examples/example-config.yaml
examples/group.py
examples/point_to_point.py
examples/slim.py
slim_bindings/__init__.py
slim_bindings/libslim_bindings.so
slim_bindings/slim_bindings.py
slim_bindings-1.0.0.dist-info/METADATA
slim_bindings-1.0.0.dist-info/WHEEL
slim_bindings-1.0.0.dist-info/entry_points.txt
slim_bindings-1.0.0.dist-info/RECORD
