Metadata-Version: 2.4
Name: slim-bindings
Version: 1.0.0
Classifier: Development Status :: 3 - Alpha
Classifier: Intended Audience :: Developers
Classifier: Topic :: Software Development :: Libraries
Classifier: Programming Language :: Python :: 3.10
Classifier: Programming Language :: Python :: 3.11
Classifier: Programming Language :: Python :: 3.12
Classifier: Programming Language :: Python :: 3.13
Classifier: Programming Language :: Python :: 3.14
Requires-Dist: pydantic>=2.0.0 ; extra == 'examples'
Requires-Dist: pydantic-settings>=2.0.0 ; extra == 'examples'
Requires-Dist: prompt-toolkit>=3.0.52 ; extra == 'examples'
Requires-Dist: pyyaml>=6.0.3 ; extra == 'examples'
Requires-Dist: tomli>=2.4.0 ; extra == 'examples'
Provides-Extra: examples
Summary: Python bindings for SLIM (Secure Low-Latency Interactive Messaging) using UniFFI
Author-email: AGNTCY Contributors <slim@agntcy.io>
License-Expression: Apache-2.0
Requires-Python: >=3.10
Project-URL: Issues, https://github.com/agntcy/slim/issues
Project-URL: Repository, https://github.com/agntcy/slim
